[
  {
    "number": 1,
    "arabic": "الفاتحة",
    "english": "Al-Fatiha",
    "length": 7
  },
  {
    "number": 2,
    "arabic": "البقرة",
    "english": "Al-Baqarah",
    "length": 286
  },
  {
    "number": 3,
    "arabic": "آل عمران",
    "english": "Aali Imran",
    "length": 200
  },
  {
    "number": 4,
    "arabic": "النساء",
    "english": "An-Nisa",
    "length": 176
  },
  {
    "number": 5,
    "arabic": "المائدة",
    "english": "Al-Maidah",
    "length": 120
  },
  {
    "number": 6,
    "arabic": "الأنعام",
    "english": "Al-Anam",
    "length": 165
  },
  {
    "number": 7,
    "arabic": "الأعراف",
    "english": "Al-Araf",
    "length": 206
  },
  {
    "number": 8,
    "arabic": "الأنفال",
    "english": "Al-Anfal",
    "length": 75
  },
  {
    "number": 9,
    "arabic": "التوبة",
    "english": "At-Tawbah",
    "length": 129
  },
  {
    "number": 10,
    "arabic": "يونس",
    "english": "Yunus",
    "length": 109
  },
  {
    "number": 11,
    "arabic": "هود",
    "english": "Hud",
    "length": 123
  },
  {
    "number": 12,
    "arabic": "يوسف",
    "english": "Yusuf",
    "length": 111
  },
  {
    "number": 13,
    "arabic": "الرعد",
    "english": "Ar-Rad",
    "length": 43
  },
  {
    "number": 14,
    "arabic": "إبراهيم",
    "english": "Ibrahim",
    "length": 52
  },
  {
    "number": 15,
    "arabic": "الحجر",
    "english": "Al-Hijr",
    "length": 99
  },
  {
    "number": 16,
    "arabic": "النحل",
    "english": "An-Nahl",
    "length": 128
  },
  {
    "number": 17,
    "arabic": "الإسراء",
    "english": "Al-Isra",
    "length": 111
  },
  {
    "number": 18,
    "arabic": "الكهف",
    "english": "Al-Kahf",
    "length": 110
  },
  {
    "number": 19,
    "arabic": "مريم",
    "english": "Maryam",
    "length": 98
  },
  {
    "number": 20,
    "arabic": "طه",
    "english": "Ta-ha",
    "length": 135
  },
  {
    "number": 21,
    "arabic": "الأنبياء",
    "english": "Al-Anbiya",
    "length": 112
  },
  {
    "number": 22,
    "arabic": "الحج",
    "english": "Al-Hajj",
    "length": 78
  },
  {
    "number": 23,
    "arabic": "المؤمنون",
    "english": "Al-Muminun",
    "length": 118
  },
  {
    "number": 24,
    "arabic": "النور",
    "english": "An-Nur",
    "length": 64
  },
  {
    "number": 25,
    "arabic": "الفرقان",
    "english": "Al-Furqan",
    "length": 77
  },
  {
    "number": 26,
    "arabic": "الشعراء",
    "english": "Ash-Shuara",
    "length": 227
  },
  {
    "number": 27,
    "arabic": "النمل",
    "english": "An-Naml",
    "length": 93
  },
  {
    "number": 28,
    "arabic": "القصص",
    "english": "Al-Qasas",
    "length": 88
  },
  {
    "number": 29,
    "arabic": "العنكبوت",
    "english": "Al-Ankabut",
    "length": 69
  },
  {
    "number": 30,
    "arabic": "الروم",
    "english": "Ar-Rum",
    "length": 60
  },
  {
    "number": 31,
    "arabic": "لقمان",
    "english": "Luqman",
    "length": 34
  },
  {
    "number": 32,
    "arabic": "السجدة",
    "english": "As-Sajdah",
    "length": 30
  },
  {
    "number": 33,
    "arabic": "الأحزاب",
    "english": "Al-Ahzab",
    "length": 73
  },
  {
    "number": 34,
    "arabic": "سبأ",
    "english": "Saba",
    "length": 54
  },
  {
    "number": 35,
    "arabic": "فاطر",
    "english": "Fatir",
    "length": 45
  },
  {
    "number": 36,
    "arabic": "يس",
    "english": "Ya-Sin",
    "length": 83
  },
  {
    "number": 37,
    "arabic": "الصافات",
    "english": "As-Saffat",
    "length": 182
  },
  {
    "number": 38,
    "arabic": "ص",
    "english": "Sad",
    "length": 88
  },
  {
    "number": 39,
    "arabic": "الزمر",
    "english": "Az-Zumar",
    "length": 75
  },
  {
    "number": 40,
    "arabic": "غافر",
    "english": "Ghafir",
    "length": 85
  },
  {
    "number": 41,
    "arabic": "فصلت",
    "english": "Fussilat",
    "length": 54
  },
  {
    "number": 42,
    "arabic": "الشورى",
    "english": "Ash-Shura",
    "length": 53
  },
  {
    "number": 43,
    "arabic": "الزخرف",
    "english": "Az-Zukhruf",
    "length": 89
  },
  {
    "number": 44,
    "arabic": "الدخان",
    "english": "Ad-Dukhan",
    "length": 59
  },
  {
    "number": 45,
    "arabic": "الجاثية",
    "english": "Al-Jathiyah",
    "length": 37
  },
  {
    "number": 46,
    "arabic": "الأحقاف",
    "english": "Al-Ahqaf",
    "length": 35
  },
  {
    "number": 47,
    "arabic": "محمد",
    "english": "Muhammad",
    "length": 38
  },
  {
    "number": 48,
    "arabic": "الفتح",
    "english": "Al-Fath",
    "length": 29
  },
  {
    "number": 49,
    "arabic": "الحجرات",
    "english": "Al-Hujurat",
    "length": 18
  },
  {
    "number": 50,
    "arabic": "ق",
    "english": "Qaf",
    "length": 45
  },
  {
    "number": 51,
    "arabic": "الذاريات",
    "english": "Adh-Dhariyat",
    "length": 60
  },
  {
    "number": 52,
    "arabic": "الطور",
    "english": "At-Tur",
    "length": 49
  },
  {
    "number": 53,
    "arabic": "النجم",
    "english": "An-Najm",
    "length": 62
  },
  {
    "number": 54,
    "arabic": "القمر",
    "english": "Al-Qamar",
    "length": 55
  },
  {
    "number": 55,
    "arabic": "الرحمن",
    "english": "Ar-Rahman",
    "length": 78
  },
  {
    "number": 56,
    "arabic": "الواقعة",
    "english": "Al-Waqiah",
    "length": 96
  },
  {
    "number": 57,
    "arabic": "الحديد",
    "english": "Al-Hadid",
    "length": 29
  },
  {
    "number": 58,
    "arabic": "المجادلة",
    "english": "Al-Mujadila",
    "length": 22
  },
  {
    "number": 59,
    "arabic": "الحشر",
    "english": "Al-Hashr",
    "length": 24
  },
  {
    "number": 60,
    "arabic": "الممتحنة",
    "english": "Al-Mumtahanah",
    "length": 13
  },
  {
    "number": 61,
    "arabic": "الصف",
    "english": "As-Saff",
    "length": 14
  },
  {
    "number": 62,
    "arabic": "الجمعة",
    "english": "Al-Jumuah",
    "length": 11
  },
  {
    "number": 63,
    "arabic": "المنافقون",
    "english": "Al-Munafiqun",
    "length": 11
  },
  {
    "number": 64,
    "arabic": "التغابن",
    "english": "At-Taghabun",
    "length": 18
  },
  {
    "number": 65,
    "arabic": "الطلاق",
    "english": "At-Talaq",
    "length": 12
  },
  {
    "number": 66,
    "arabic": "التحريم",
    "english": "At-Tahrim",
    "length": 12
  },
  {
    "number": 67,
    "arabic": "الملك",
    "english": "Al-Mulk",
    "length": 30
  },
  {
    "number": 68,
    "arabic": "القلم",
    "english": "Al-Qalam",
    "length": 52
  },
  {
    "number": 69,
    "arabic": "الحاقة",
    "english": "Al-Haqqah",
    "length": 52
  },
  {
    "number": 70,
    "arabic": "المعارج",
    "english": "Al-Maarij",
    "length": 44
  },
  {
    "number": 71,
    "arabic": "نوح",
    "english": "Nuh",
    "length": 28
  },
  {
    "number": 72,
    "arabic": "الجن",
    "english": "Al-Jinn",
    "length": 28
  },
  {
    "number": 73,
    "arabic": "المزمل",
    "english": "Al-Muzzammil",
    "length": 20
  },
  {
    "number": 74,
    "arabic": "المدثر",
    "english": "Al-Muddaththir",
    "length": 56
  },
  {
    "number": 75,
    "arabic": "القيامة",
    "english": "Al-Qiyamah",
    "length": 40
  },
  {
    "number": 76,
    "arabic": "الإنسان",
    "english": "Al-Insan",
    "length": 31
  },
  {
    "number": 77,
    "arabic": "المرسلات",
    "english": "Al-Mursalat",
    "length": 50
  },
  {
    "number": 78,
    "arabic": "النبأ",
    "english": "An-Naba",
    "length": 40
  },
  {
    "number": 79,
    "arabic": "النازعات",
    "english": "An-Naziat",
    "length": 46
  },
  {
    "number": 80,
    "arabic": "عبس",
    "english": "Abasa",
    "length": 42
  },
  {
    "number": 81,
    "arabic": "التكوير",
    "english": "At-Takwir",
    "length": 29
  },
  {
    "number": 82,
    "arabic": "الإنفطار",
    "english": "Al-Infitar",
    "length": 19
  },
  {
    "number": 83,
    "arabic": "المطففين",
    "english": "Al-Mutaffifin",
    "length": 36
  },
  {
    "number": 84,
    "arabic": "الإنشقاق",
    "english": "Al-Inshiqaq",
    "length": 25
  },
  {
    "number": 85,
    "arabic": "البروج",
    "english": "Al-Buruj",
    "length": 22
  },
  {
    "number": 86,
    "arabic": "الطارق",
    "english": "At-Tariq",
    "length": 17
  },
  {
    "number": 87,
    "arabic": "الأعلى",
    "english": "Al-Ala",
    "length": 19
  },
  {
    "number": 88,
    "arabic": "الغاشية",
    "english": "Al-Ghashiyah",
    "length": 26
  },
  {
    "number": 89,
    "arabic": "الفجر",
    "english": "Al-Fajr",
    "length": 30
  },
  {
    "number": 90,
    "arabic": "البلد",
    "english": "Al-Balad",
    "length": 20
  },
  {
    "number": 91,
    "arabic": "الشمس",
    "english": "Ash-Shams",
    "length": 15
  },
  {
    "number": 92,
    "arabic": "الليل",
    "english": "Al-Layl",
    "length": 21
  },
  {
    "number": 93,
    "arabic": "الضحى",
    "english": "Ad-Duha",
    "length": 11
  },
  {
    "number": 94,
    "arabic": "الشرح",
    "english": "Ash-Sharh",
    "length": 8
  },
  {
    "number": 95,
    "arabic": "التين",
    "english": "At-Tin",
    "length": 8
  },
  {
    "number": 96,
    "arabic": "العلق",
    "english": "Al-Alaq",
    "length": 19
  },
  {
    "number": 97,
    "arabic": "القدر",
    "english": "Al-Qadr",
    "length": 5
  },
  {
    "number": 98,
    "arabic": "البينة",
    "english": "Al-Bayyinah",
    "length": 8
  },
  {
    "number": 99,
    "arabic": "الزلزلة",
    "english": "Az-Zalzalah",
    "length": 8
  },
  {
    "number": 100,
    "arabic": "العاديات",
    "english": "Al-Adiyat",
    "length": 11
  },
  {
    "number": 101,
    "arabic": "القارعة",
    "english": "Al-Qariah",
    "length": 11
  },
  {
    "number": 102,
    "arabic": "التكاثر",
    "english": "At-Takathur",
    "length": 8
  },
  {
    "number": 103,
    "arabic": "العصر",
    "english": "Al-Asr",
    "length": 3
  },
  {
    "number": 104,
    "arabic": "الهمزة",
    "english": "Al-Humazah",
    "length": 9
  },
  {
    "number": 105,
    "arabic": "الفيل",
    "english": "Al-Fil",
    "length": 5
  },
  {
    "number": 106,
    "arabic": "قريش",
    "english": "Quraysh",
    "length": 4
  },
  {
    "number": 107,
    "arabic": "الماعون",
    "english": "Al-Maun",
    "length": 7
  },
  {
    "number": 108,
    "arabic": "الكوثر",
    "english": "Al-Kawthar",
    "length": 3
  },
  {
    "number": 109,
    "arabic": "الكافرون",
    "english": "Al-Kafirun",
    "length": 6
  },
  {
    "number": 110,
    "arabic": "النصر",
    "english": "An-Nasr",
    "length": 3
  },
  {
    "number": 111,
    "arabic": "المسد",
    "english": "Al-Masad",
    "length": 5
  },
  {
    "number": 112,
    "arabic": "الإخلاص",
    "english": "Al-Ikhlas",
    "length": 4
  },
  {
    "number": 113,
    "arabic": "الفلق",
    "english": "Al-Falaq",
    "length": 5
  },
  {
    "number": 114,
    "arabic": "الناس",
    "english": "An-Nas",
    "length": 6
  }
]
